AUTHORS
ChangeLog
MANIFEST.in
README.rst
requirements.txt
setup.cfg
setup.py
leonardo_module_blog/__init__.py
leonardo_module_blog/models.py
leonardo_module_blog/overrides.py
leonardo_module_blog/search_indexes.py
leonardo_module_blog.egg-info/PKG-INFO
leonardo_module_blog.egg-info/SOURCES.txt
leonardo_module_blog.egg-info/dependency_links.txt
leonardo_module_blog.egg-info/not-zip-safe
leonardo_module_blog.egg-info/pbr.json
leonardo_module_blog.egg-info/requires.txt
leonardo_module_blog.egg-info/top_level.txt
leonardo_module_blog/locale/cs/LC_MESSAGES/django.po
leonardo_module_blog/locale/de/LC_MESSAGES/django.po
leonardo_module_blog/locale/sk/LC_MESSAGES/django.po
leonardo_module_blog/templates/elephantblog/_disqus_comments.html
leonardo_module_blog/templates/elephantblog/entry_archive.html
leonardo_module_blog/templates/elephantblog/entry_detail.html
leonardo_module_blog/templates/search/indexes/elephantblog/entry_text.txt
leonardo_module_blog/templates/widget/blogcategories/default.html
leonardo_module_blog/templates/widget/pagetitle/blog.html
leonardo_module_blog/templates/widget/recentblogposts/cycle.html
leonardo_module_blog/templates/widget/recentblogposts/default.html
leonardo_module_blog/templates/widget/recentblogposts/grid.html
leonardo_module_blog/templatetags/__init__.py
leonardo_module_blog/templatetags/blog.py
leonardo_module_blog/widget/__init__.py
leonardo_module_blog/widget/blogcategories/__init__.py
leonardo_module_blog/widget/blogcategories/models.py
leonardo_module_blog/widget/recentblogposts/__init__.py
leonardo_module_blog/widget/recentblogposts/models.py